alphacompiler/__init__.py
alphacompiler/data/NASDAQ.py
alphacompiler/data/NASDAQ_sector_code_loader.py
alphacompiler/data/SHARADAR_sector_code_loader.py
alphacompiler/data/SHARADAR_sectors.py
alphacompiler/data/__init__.py
alphacompiler/data/load_quandl_sf1.py
alphacompiler/data/quandl_fundamentals.py
alphacompiler/data/sf1_fundamentals.py
alphacompiler/data/loaders/__init__.py
alphacompiler/data/loaders/crsp_daily_stock.py
alphacompiler/data/loaders/sep_quandl.py
alphacompiler/data/loaders/zacks_quandl.py
alphacompiler/util/__init__.py
alphacompiler/util/benchmarks.py
alphacompiler/util/load_extensions.py
alphacompiler/util/quandl_tools.py
alphacompiler/util/sparse_data.py
alphacompiler/util/zipline_data_tools.py
alpha_compiler_vk-0.1.3.dist-info/METADATA
alpha_compiler_vk-0.1.3.dist-info/WHEEL
alpha_compiler_vk-0.1.3.dist-info/top_level.txt
alpha_compiler_vk-0.1.3.dist-info/RECORD
